{"generatedOn":"2025-10-17T16:53:30.425497Z","nodes":{"libraries":{"percentile":0.7,"similarity":0.6614000572669394,"totalPairs":21,"distribution":[{"percentile":0.7,"count":15}]},"cli":{"percentile":0.5,"similarity":0.6385391172734987,"totalPairs":6,"distribution":[{"percentile":0.5,"count":4}]},"dotnet":{"percentile":0.5,"similarity":0.785071741622752,"totalPairs":1,"distribution":[{"percentile":0.5,"count":1}]},"extensions":{"percentile":0.5,"similarity":0.5844567046006856,"totalPairs":3,"distribution":[{"percentile":0.5,"count":2}]},"csharp":{"percentile":0.7,"similarity":0.711816197340724,"totalPairs":8,"distribution":[{"percentile":0.7,"count":6}]}}}